{
    "name": "sparrow-flir",
    "build": {
        "dockerfile": "../Dockerfile",
        "context": ".."
    },
    "settings": {
        "python.pythonPath": "/usr/local/bin/python",
        "python.languageServer": "Pylance",
        "python.linting.enabled": true,
        // pydocstyle
        "python.linting.pydocstyleEnabled": true,
        "python.linting.pydocstylePath": "/usr/local/bin/pydocstyle",
        // black
        "python.formatting.blackPath": "/usr/local/bin/black",
        "python.formatting.provider": "black",
        "[python]": {
            "editor.formatOnSave": true,
            "editor.codeActionsOnSave": {
                "source.organizeImports": true
            },
        },
        // isort
        "python.sortImports.path": "/usr/local/bin/isort",
        // pylint
        "python.linting.pylintEnabled": true,
        "python.linting.pylintPath": "/usr/local/bin/pylint",
        // pytest
        "python.testing.pytestArgs": [
            "sparrow_flir"
        ],
        "python.testing.pytestEnabled": true,
    },
    "extensions": [
        "ms-python.python",
        "ms-python.vscode-pylance"
    ],
    "mounts": [
        "source=projectname-bashhistory,target=/commandhistory,type=volume",
        "source=${localEnv:HOME}/.ssh,target=/root/.ssh,type=bind,consistency=cached,readonly",
    ],
    "workspaceFolder": "/code",
    "workspaceMount": "source=${localWorkspaceFolder},target=/code,type=bind,consistency=cached",
    "runArgs": [
        "--ipc=host",
    ],
    "postCreateCommand": "pip install -e .",
}